{
  "vaultName": "Asras legender",
  "lastExport": 1714862378731,
  "pluginVersion": "1.8.01",
  "validBodyClasses": "publish css-settings-manager theme-dark show-inline-title basic-pathfinder-2e-layout-theme-default pathfinder-2e-action-layout-theme-default pathfinder-2e-hazard-layout-theme-default pathfinder-2e-influence-layout-theme-default pathfinder-2e-misc-layout-theme-default pathfinder-2e-quest-layout-theme-default pathfinder-2e-settlement-layout-theme-default sizing-readable check-color check-bg",
  "useCustomHeadContent": false,
  "useCustomFavicon": false,
  "files": [
    "World/Guder/Aeon.md",
    "World/Guder/Drexel.md",
    "World/Guder/Eldrin.md",
    "World/Guder/Lysandra.md",
    "World/Guder/Miran.md",
    "World/Guder/Noctra.md",
    "World/Guder/Syrax.md",
    "World/Guder/Tharros.md",
    "World/Guder/Vox.md",
    "World/Guder/Zephyra.md",
    "World/Lokationer/Riverton/Gården.md",
    "World/Lokationer/Zephia/ZephiaMap.md",
    "World/Lokationer/Auria.md",
    "World/Lokationer/Riverton.md",
    "World/Lokationer/Zephia.md",
    "World/NPCs/Aleric.md",
    "World/NPCs/Brakka Giftpil.md",
    "World/NPCs/Krogar Ironfist.md",
    "World/Asra.md",
    "README.md",
    "lib/media/aeon.jpg",
    "lib/media/drexel.jpg",
    "lib/media/eldrin.jpg",
    "lib/media/lysandra.jpg",
    "lib/media/miran.jpeg",
    "lib/media/noctra.jpeg",
    "lib/media/syrax.jpeg",
    "lib/media/tharros.jpeg",
    "lib/media/vox.jpeg",
    "lib/media/zephyra.jpeg",
    "lib/media/gården.jpg",
    "lib/media/zephia.png",
    "lib/media/auria.png",
    "lib/media/riverton.png",
    "lib/media/alaric.jpg",
    "lib/media/brakka.jpg",
    "lib/media/krogar.jpg",
    "lib/scripts/graph-wasm.wasm",
    "lib/fonts/94f2f163d4b698242fef.otf",
    "lib/fonts/72505e6a122c6acd5471.woff2",
    "lib/fonts/2d5198822ab091ce4305.woff2",
    "lib/fonts/c8ba52b05a9ef10f4758.woff2",
    "lib/fonts/cb10ffd7684cd9836a05.woff2",
    "lib/fonts/b5f0f109bc88052d4000.woff2",
    "lib/fonts/cbe0ae49c52c920fd563.woff2",
    "lib/fonts/535a6cf662596b3bd6a6.woff2",
    "lib/fonts/70cc7ff27245e82ad414.ttf",
    "lib/fonts/454577c22304619db035.ttf",
    "lib/fonts/52ac8f3034507f1d9e53.ttf",
    "lib/fonts/05b618077343fbbd92b7.ttf",
    "lib/fonts/4bb6ac751d1c5478ff3a.woff2",
    "lib/media/874d8b8e340f75575caa.svg",
    "lib/html/file-tree.html",
    "lib/scripts/webpage.js",
    "lib/scripts/graph-view.js",
    "lib/scripts/graph-wasm.js",
    "lib/scripts/graph-render-worker.js",
    "lib/scripts/tinycolor.js",
    "lib/scripts/pixi.js",
    "lib/scripts/minisearch.js",
    "lib/media/favicon.png",
    "lib/scripts/graph-data.js",
    "lib/styles/obsidian.css",
    "lib/styles/other-plugins.css",
    "lib/styles/theme.css",
    "lib/styles/global-variable-styles.css",
    "lib/styles/supported-plugins.css",
    "lib/styles/main-styles.css"
  ],
  "mainDependencies": [
    "lib/scripts/graph-wasm.wasm",
    "lib/fonts/94f2f163d4b698242fef.otf",
    "lib/fonts/72505e6a122c6acd5471.woff2",
    "lib/fonts/2d5198822ab091ce4305.woff2",
    "lib/fonts/c8ba52b05a9ef10f4758.woff2",
    "lib/fonts/cb10ffd7684cd9836a05.woff2",
    "lib/fonts/b5f0f109bc88052d4000.woff2",
    "lib/fonts/cbe0ae49c52c920fd563.woff2",
    "lib/fonts/535a6cf662596b3bd6a6.woff2",
    "lib/fonts/70cc7ff27245e82ad414.ttf",
    "lib/fonts/454577c22304619db035.ttf",
    "lib/fonts/52ac8f3034507f1d9e53.ttf",
    "lib/fonts/05b618077343fbbd92b7.ttf",
    "lib/fonts/4bb6ac751d1c5478ff3a.woff2",
    "lib/media/874d8b8e340f75575caa.svg",
    "lib/html/file-tree.html",
    "lib/scripts/webpage.js",
    "lib/scripts/graph-view.js",
    "lib/scripts/graph-wasm.js",
    "lib/scripts/graph-render-worker.js",
    "lib/scripts/tinycolor.js",
    "lib/scripts/pixi.js",
    "lib/scripts/minisearch.js",
    "lib/media/favicon.png",
    "lib/scripts/graph-data.js",
    "lib/styles/obsidian.css",
    "lib/styles/other-plugins.css",
    "lib/styles/theme.css",
    "lib/styles/global-variable-styles.css",
    "lib/styles/supported-plugins.css",
    "lib/styles/main-styles.css"
  ],
  "fileInfo": {
    "World/Guder/Aeon.md": {
      "modifiedTime": 1714862378731,
      "sourceSize": 1629,
      "exportedPath": "world/guder/aeon.html",
      "dependencies": [
        "lib/media/aeon.jpg"
      ]
    },
    "World/Guder/Drexel.md": {
      "modifiedTime": 1714862378731,
      "sourceSize": 845,
      "exportedPath": "world/guder/drexel.html",
      "dependencies": [
        "lib/media/drexel.jpg"
      ]
    },
    "World/Guder/Eldrin.md": {
      "modifiedTime": 1714862378731,
      "sourceSize": 851,
      "exportedPath": "world/guder/eldrin.html",
      "dependencies": [
        "lib/media/eldrin.jpg"
      ]
    },
    "World/Guder/Lysandra.md": {
      "modifiedTime": 1714862378731,
      "sourceSize": 918,
      "exportedPath": "world/guder/lysandra.html",
      "dependencies": [
        "lib/media/lysandra.jpg"
      ]
    },
    "World/Guder/Miran.md": {
      "modifiedTime": 1714862378731,
      "sourceSize": 876,
      "exportedPath": "world/guder/miran.html",
      "dependencies": [
        "lib/media/miran.jpeg"
      ]
    },
    "World/Guder/Noctra.md": {
      "modifiedTime": 1714862378731,
      "sourceSize": 838,
      "exportedPath": "world/guder/noctra.html",
      "dependencies": [
        "lib/media/noctra.jpeg"
      ]
    },
    "World/Guder/Syrax.md": {
      "modifiedTime": 1714862378731,
      "sourceSize": 906,
      "exportedPath": "world/guder/syrax.html",
      "dependencies": [
        "lib/media/syrax.jpeg"
      ]
    },
    "World/Guder/Tharros.md": {
      "modifiedTime": 1714862378731,
      "sourceSize": 896,
      "exportedPath": "world/guder/tharros.html",
      "dependencies": [
        "lib/media/tharros.jpeg"
      ]
    },
    "World/Guder/Vox.md": {
      "modifiedTime": 1714862378731,
      "sourceSize": 834,
      "exportedPath": "world/guder/vox.html",
      "dependencies": [
        "lib/media/vox.jpeg"
      ]
    },
    "World/Guder/Zephyra.md": {
      "modifiedTime": 1714862378731,
      "sourceSize": 852,
      "exportedPath": "world/guder/zephyra.html",
      "dependencies": [
        "lib/media/zephyra.jpeg"
      ]
    },
    "World/Lokationer/Riverton/Gården.md": {
      "modifiedTime": 1714862378731,
      "sourceSize": 1104,
      "exportedPath": "world/lokationer/riverton/gården.html",
      "dependencies": [
        "lib/media/gården.jpg"
      ]
    },
    "World/Lokationer/Zephia/ZephiaMap.md": {
      "modifiedTime": 1714862378731,
      "sourceSize": 1611,
      "exportedPath": "world/lokationer/zephia/zephiamap.html",
      "dependencies": [
        "lib/media/zephia.png"
      ]
    },
    "World/Lokationer/Auria.md": {
      "modifiedTime": 1714862378731,
      "sourceSize": 1548,
      "exportedPath": "world/lokationer/auria.html",
      "dependencies": [
        "lib/media/auria.png",
        "lib/media/auria.png"
      ]
    },
    "World/Lokationer/Riverton.md": {
      "modifiedTime": 1714862378731,
      "sourceSize": 1311,
      "exportedPath": "world/lokationer/riverton.html",
      "dependencies": [
        "lib/media/riverton.png"
      ]
    },
    "World/Lokationer/Zephia.md": {
      "modifiedTime": 1714862378731,
      "sourceSize": 3609,
      "exportedPath": "world/lokationer/zephia.html",
      "dependencies": [
        "lib/media/zephia.png",
        "lib/media/zephia.png"
      ]
    },
    "World/NPCs/Aleric.md": {
      "modifiedTime": 1714862378731,
      "sourceSize": 1091,
      "exportedPath": "world/npcs/aleric.html",
      "dependencies": [
        "lib/media/alaric.jpg"
      ]
    },
    "World/NPCs/Brakka Giftpil.md": {
      "modifiedTime": 1714862378731,
      "sourceSize": 1107,
      "exportedPath": "world/npcs/brakka-giftpil.html",
      "dependencies": [
        "lib/media/brakka.jpg"
      ]
    },
    "World/NPCs/Krogar Ironfist.md": {
      "modifiedTime": 1714862378731,
      "sourceSize": 1070,
      "exportedPath": "world/npcs/krogar-ironfist.html",
      "dependencies": [
        "lib/media/krogar.jpg"
      ]
    },
    "World/Asra.md": {
      "modifiedTime": 1714862378731,
      "sourceSize": 3175,
      "exportedPath": "world/asra.html",
      "dependencies": []
    },
    "README.md": {
      "modifiedTime": 1714861639468,
      "sourceSize": 17,
      "exportedPath": "readme.html",
      "dependencies": []
    },
    "lib/media/aeon.jpg": {
      "modifiedTime": 1714862378731,
      "sourceSize": 220865,
      "exportedPath": "lib/media/aeon.jpg",
      "dependencies": []
    },
    "lib/media/drexel.jpg": {
      "modifiedTime": 1714862378731,
      "sourceSize": 258396,
      "exportedPath": "lib/media/drexel.jpg",
      "dependencies": []
    },
    "lib/media/eldrin.jpg": {
      "modifiedTime": 1714862378731,
      "sourceSize": 163623,
      "exportedPath": "lib/media/eldrin.jpg",
      "dependencies": []
    },
    "lib/media/lysandra.jpg": {
      "modifiedTime": 1714862378731,
      "sourceSize": 217790,
      "exportedPath": "lib/media/lysandra.jpg",
      "dependencies": []
    },
    "lib/media/miran.jpeg": {
      "modifiedTime": 1714862378731,
      "sourceSize": 220859,
      "exportedPath": "lib/media/miran.jpeg",
      "dependencies": []
    },
    "lib/media/noctra.jpeg": {
      "modifiedTime": 1714862378731,
      "sourceSize": 158593,
      "exportedPath": "lib/media/noctra.jpeg",
      "dependencies": []
    },
    "lib/media/syrax.jpeg": {
      "modifiedTime": 1714862378731,
      "sourceSize": 306700,
      "exportedPath": "lib/media/syrax.jpeg",
      "dependencies": []
    },
    "lib/media/tharros.jpeg": {
      "modifiedTime": 1714862378731,
      "sourceSize": 195507,
      "exportedPath": "lib/media/tharros.jpeg",
      "dependencies": []
    },
    "lib/media/vox.jpeg": {
      "modifiedTime": 1714862378731,
      "sourceSize": 293466,
      "exportedPath": "lib/media/vox.jpeg",
      "dependencies": []
    },
    "lib/media/zephyra.jpeg": {
      "modifiedTime": 1714862378731,
      "sourceSize": 179466,
      "exportedPath": "lib/media/zephyra.jpeg",
      "dependencies": []
    },
    "lib/media/gården.jpg": {
      "modifiedTime": 1714862378731,
      "sourceSize": 213447,
      "exportedPath": "lib/media/gården.jpg",
      "dependencies": []
    },
    "lib/media/zephia.png": {
      "modifiedTime": 1714862378731,
      "sourceSize": 5532592,
      "exportedPath": "lib/media/zephia.png",
      "dependencies": []
    },
    "lib/media/auria.png": {
      "modifiedTime": 1714862378731,
      "sourceSize": 2689814,
      "exportedPath": "lib/media/auria.png",
      "dependencies": []
    },
    "lib/media/riverton.png": {
      "modifiedTime": 1714862378731,
      "sourceSize": 1153102,
      "exportedPath": "lib/media/riverton.png",
      "dependencies": []
    },
    "lib/media/alaric.jpg": {
      "modifiedTime": 1714862378731,
      "sourceSize": 203826,
      "exportedPath": "lib/media/alaric.jpg",
      "dependencies": []
    },
    "lib/media/brakka.jpg": {
      "modifiedTime": 1714862378731,
      "sourceSize": 181440,
      "exportedPath": "lib/media/brakka.jpg",
      "dependencies": []
    },
    "lib/media/krogar.jpg": {
      "modifiedTime": 1714862378731,
      "sourceSize": 223325,
      "exportedPath": "lib/media/krogar.jpg",
      "dependencies": []
    },
    "lib/scripts/graph-wasm.wasm": {
      "modifiedTime": 1714862378731,
      "sourceSize": 23377,
      "exportedPath": "lib/scripts/graph-wasm.wasm",
      "dependencies": []
    },
    "lib/fonts/94f2f163d4b698242fef.otf": {
      "modifiedTime": 1714862378731,
      "sourceSize": 66800,
      "exportedPath": "lib/fonts/94f2f163d4b698242fef.otf",
      "dependencies": []
    },
    "lib/fonts/72505e6a122c6acd5471.woff2": {
      "modifiedTime": 1714862378731,
      "sourceSize": 104232,
      "exportedPath": "lib/fonts/72505e6a122c6acd5471.woff2",
      "dependencies": []
    },
    "lib/fonts/2d5198822ab091ce4305.woff2": {
      "modifiedTime": 1714862378731,
      "sourceSize": 104332,
      "exportedPath": "lib/fonts/2d5198822ab091ce4305.woff2",
      "dependencies": []
    },
    "lib/fonts/c8ba52b05a9ef10f4758.woff2": {
      "modifiedTime": 1714862378731,
      "sourceSize": 98868,
      "exportedPath": "lib/fonts/c8ba52b05a9ef10f4758.woff2",
      "dependencies": []
    },
    "lib/fonts/cb10ffd7684cd9836a05.woff2": {
      "modifiedTime": 1714862378731,
      "sourceSize": 106876,
      "exportedPath": "lib/fonts/cb10ffd7684cd9836a05.woff2",
      "dependencies": []
    },
    "lib/fonts/b5f0f109bc88052d4000.woff2": {
      "modifiedTime": 1714862378731,
      "sourceSize": 105804,
      "exportedPath": "lib/fonts/b5f0f109bc88052d4000.woff2",
      "dependencies": []
    },
    "lib/fonts/cbe0ae49c52c920fd563.woff2": {
      "modifiedTime": 1714862378731,
      "sourceSize": 106108,
      "exportedPath": "lib/fonts/cbe0ae49c52c920fd563.woff2",
      "dependencies": []
    },
    "lib/fonts/535a6cf662596b3bd6a6.woff2": {
      "modifiedTime": 1714862378731,
      "sourceSize": 111708,
      "exportedPath": "lib/fonts/535a6cf662596b3bd6a6.woff2",
      "dependencies": []
    },
    "lib/fonts/70cc7ff27245e82ad414.ttf": {
      "modifiedTime": 1714862378731,
      "sourceSize": 192740,
      "exportedPath": "lib/fonts/70cc7ff27245e82ad414.ttf",
      "dependencies": []
    },
    "lib/fonts/454577c22304619db035.ttf": {
      "modifiedTime": 1714862378731,
      "sourceSize": 161376,
      "exportedPath": "lib/fonts/454577c22304619db035.ttf",
      "dependencies": []
    },
    "lib/fonts/52ac8f3034507f1d9e53.ttf": {
      "modifiedTime": 1714862378731,
      "sourceSize": 191568,
      "exportedPath": "lib/fonts/52ac8f3034507f1d9e53.ttf",
      "dependencies": []
    },
    "lib/fonts/05b618077343fbbd92b7.ttf": {
      "modifiedTime": 1714862378731,
      "sourceSize": 155288,
      "exportedPath": "lib/fonts/05b618077343fbbd92b7.ttf",
      "dependencies": []
    },
    "lib/fonts/4bb6ac751d1c5478ff3a.woff2": {
      "modifiedTime": 1714862378731,
      "sourceSize": 7876,
      "exportedPath": "lib/fonts/4bb6ac751d1c5478ff3a.woff2",
      "dependencies": []
    },
    "lib/media/874d8b8e340f75575caa.svg": {
      "modifiedTime": 1714862378731,
      "sourceSize": 317,
      "exportedPath": "lib/media/874d8b8e340f75575caa.svg",
      "dependencies": []
    },
    "lib/html/file-tree.html": {
      "modifiedTime": 1714862378731,
      "sourceSize": 15114,
      "exportedPath": "lib/html/file-tree.html",
      "dependencies": []
    },
    "lib/scripts/webpage.js": {
      "modifiedTime": 1714862378731,
      "sourceSize": 47290,
      "exportedPath": "lib/scripts/webpage.js",
      "dependencies": []
    },
    "lib/scripts/graph-view.js": {
      "modifiedTime": 1714862378731,
      "sourceSize": 15519,
      "exportedPath": "lib/scripts/graph-view.js",
      "dependencies": []
    },
    "lib/scripts/graph-wasm.js": {
      "modifiedTime": 1714862378731,
      "sourceSize": 14021,
      "exportedPath": "lib/scripts/graph-wasm.js",
      "dependencies": []
    },
    "lib/scripts/graph-render-worker.js": {
      "modifiedTime": 1714862378731,
      "sourceSize": 5179,
      "exportedPath": "lib/scripts/graph-render-worker.js",
      "dependencies": []
    },
    "lib/scripts/tinycolor.js": {
      "modifiedTime": 1714862378731,
      "sourceSize": 29832,
      "exportedPath": "lib/scripts/tinycolor.js",
      "dependencies": []
    },
    "lib/scripts/pixi.js": {
      "modifiedTime": 1714862378731,
      "sourceSize": 449509,
      "exportedPath": "lib/scripts/pixi.js",
      "dependencies": []
    },
    "lib/scripts/minisearch.js": {
      "modifiedTime": 1714862378731,
      "sourceSize": 29422,
      "exportedPath": "lib/scripts/minisearch.js",
      "dependencies": []
    },
    "lib/media/favicon.png": {
      "modifiedTime": 1714862378731,
      "sourceSize": 1105,
      "exportedPath": "lib/media/favicon.png",
      "dependencies": []
    },
    "lib/scripts/graph-data.js": {
      "modifiedTime": 1714862378731,
      "sourceSize": 1113,
      "exportedPath": "lib/scripts/graph-data.js",
      "dependencies": []
    },
    "lib/styles/obsidian.css": {
      "modifiedTime": 1714862378731,
      "sourceSize": 157722,
      "exportedPath": "lib/styles/obsidian.css",
      "dependencies": []
    },
    "lib/styles/other-plugins.css": {
      "modifiedTime": 1714862378731,
      "sourceSize": 1449502,
      "exportedPath": "lib/styles/other-plugins.css",
      "dependencies": []
    },
    "lib/styles/theme.css": {
      "modifiedTime": 1714862378731,
      "sourceSize": 701815,
      "exportedPath": "lib/styles/theme.css",
      "dependencies": []
    },
    "lib/styles/global-variable-styles.css": {
      "modifiedTime": 1714862378731,
      "sourceSize": 236,
      "exportedPath": "lib/styles/global-variable-styles.css",
      "dependencies": []
    },
    "lib/styles/supported-plugins.css": {
      "modifiedTime": 1714862378731,
      "sourceSize": 21089,
      "exportedPath": "lib/styles/supported-plugins.css",
      "dependencies": []
    },
    "lib/styles/main-styles.css": {
      "modifiedTime": 1714862378731,
      "sourceSize": 23130,
      "exportedPath": "lib/styles/main-styles.css",
      "dependencies": []
    }
  }
}